{
  "appId": "com.principia.app",
  "productName": "Principia",
  "directories": {
    "output": "dist-electron"
  },
  "files": [
    "electron/**/*",
    "dist/**/*",
    "package.json"
  ],
  "extraResources": [
    {
      "from": "electron/app.exe",
      "to": "app.exe"
    },
    {
      "from": "electron/app",
      "to": "app"
    },
    {
      "from": "electron/app",
      "to": "app"
    }
  ],
  "win": {
    "target": ["nsis", "portable"],
    "icon": "public/favicon.png"
  },
  "mac": {
    "target": ["dmg", "zip"],
    "icon": "public/favicon.png",
    "category": "public.app-category.utilities"
  },
  "linux": {
    "target": ["AppImage"],
    "icon": "public/favicon.png",
    "category": "Utility"
  }
}
